bindvar.py
bindvar-2023.5.0.dist-info/LICENSE.txt
bindvar-2023.5.0.dist-info/WHEEL
bindvar-2023.5.0.dist-info/METADATA
bindvar-2023.5.0.dist-info/RECORD
