Metadata-Version: 2.1
Name: bindvar
Version: 2023.5.0
Summary: Bind variables to Python functions.
Author-email: Nicolas Tessore <n.tessore@ucl.ac.uk>
Requires-Python: >=3.8
Classifier: License :: OSI Approved :: MIT License
Project-URL: Homepage, https://github.com/ntessore/bindvar
Project-URL: Issues, https://github.com/ntessore/bindvar/issues
